gfr/__main__.py
gfr/app.py
gfr/assets/changelog.py
gfr/assets/mit.py
gfr/commands/ac.py
gfr/commands/acp.py
gfr/commands/add.py
gfr/commands/addasset.py
gfr/commands/addmicro.py
gfr/commands/bugfix.py
gfr/commands/commit.py
gfr/commands/create.py
gfr/commands/dev.py
gfr/commands/doc.py
gfr/commands/feature.py
gfr/commands/hello.py
gfr/commands/init.py
gfr/commands/link.py
gfr/commands/push.py
gfr/commands/release.py
gfr/commands/status.py
gfr/utils/command_helpers.py
gfr/utils/config.py
gfr/utils/console.py
gfr/utils/git/__init__.py
gfr/utils/git/exceptions.py
gfr/utils/git/operations.py
gfr/utils/git/repo_status.py
gfr/utils/github/__init__.py
gfr/utils/github/api.py
gfr/utils/github/exceptions.py
gfr/utils/github/issues.py
gfr/utils/github/pull_requests.py
gfr/utils/github/repositories.py
gfr-1.1.2.dist-info/entry_points.txt
gfr-1.1.2.dist-info/LICENSE
gfr-1.1.2.dist-info/METADATA
gfr-1.1.2.dist-info/WHEEL
gfr-1.1.2.dist-info/RECORD
